residual2vec/__init__.py
residual2vec/node_samplers.py
residual2vec/random_walk_sampler.py
residual2vec/residual2vec.py
residual2vec/residual2vec_sgd.py
residual2vec/utils.py
residual2vec/word2vec.py
residual2vec-0.0.12.dist-info/METADATA
residual2vec-0.0.12.dist-info/WHEEL
residual2vec-0.0.12.dist-info/top_level.txt
residual2vec-0.0.12.dist-info/RECORD
