Metadata-Version: 2.1
Name: residual2vec
Version: 0.0.12
Summary: residual2vec: debiasing graph embedding with random graphs
Home-page: https://github.com/skojaku/residual2vec
Author: Sadamori Kojaku
License: MIT
Keywords: graph embedding
Classifier: Development Status :: 3 - Alpha
Classifier: Intended Audience :: Science/Research
Classifier: Topic :: Software Development
Classifier: License :: OSI Approved :: MIT License
Classifier: Programming Language :: Python :: 3.7
Classifier: Programming Language :: Python :: 3.8
Classifier: Programming Language :: Python :: 3.9
Requires-Dist: faiss-cpu
Requires-Dist: numpy
Requires-Dist: scikit-learn
Requires-Dist: scipy
Requires-Dist: numba
Requires-Dist: torch
Requires-Dist: tqdm
